setup.py
CFA/__init__.py
CFA.egg-info/PKG-INFO
CFA.egg-info/SOURCES.txt
CFA.egg-info/dependency_links.txt
CFA.egg-info/not-zip-safe
CFA.egg-info/top_level.txt
CFA/CTP/ApiStruct.py
CFA/CTP/MdApi.cp37-win_amd64.pyd
CFA/CTP/TraderApi.cp37-win_amd64.pyd
CFA/CTP/__init__.py
CFA/CTP/thostmduserapi_se.dll
CFA/CTP/thosttraderapi_se.dll
CFA/utils/__init__.py
CFA/utils/base_field.py
CFA/utils/check_service.py
E:/pip/AlgoTrader/src/CFA/CTP/MdApi.cpp
E:/pip/AlgoTrader/src/CFA/CTP/TraderApi.cpp