Metadata-Version: 1.2
Name: CFA
Version: 2.0
Summary: China Futures Assistant 中国期货助手
Home-page: UNKNOWN
Author: China Futures Assistant
Author-email: 736753634@qq.com
License: MIT
Keywords: CTP Simnow 量化 程序化 算法交易 quant quantitative algotrading
Platform: Windows
Platform: Linux
Requires-Python: >=3.7
